[
	{
		"key": "datr",
		"value": "9i5lYdOXVpjbs56s1jWtjnxB",
		"domain": "facebook.com",
		"path": "/",
		"hostOnly": false,
		"creation": "2021-10-12T08:10:13.262Z",
		"lastAccessed": "2021-10-12T08:10:14.471Z"
	},
	{
		"key": "sb",
		"value": "9i5lYYXpbvLBtWOYsGpUFCAk",
		"domain": "facebook.com",
		"path": "/",
		"hostOnly": false,
		"creation": "2021-10-12T08:10:13.268Z",
		"lastAccessed": "2021-10-12T08:10:14.471Z"
	},
	{
		"key": "m_pixel_ratio",
		"value": "1.806249976158142",
		"domain": "facebook.com",
		"path": "/",
		"hostOnly": false,
		"creation": "2021-10-12T08:10:13.272Z",
		"lastAccessed": "2021-10-12T08:10:14.471Z"
	},
	{
		"key": "fr",
		"value": "0vkc5mF7qcuOOD2zY.AWWEf1ZgGMNtPQUtgAwvrOFGLhw.BhZS72.wi.AAA.0.0.BhZS7_.AWVt_Ji-5gc",
		"domain": "facebook.com",
		"path": "/",
		"hostOnly": false,
		"creation": "2021-10-12T08:10:13.276Z",
		"lastAccessed": "2021-10-12T08:10:14.471Z"
	},
	{
		"key": "c_user",
		"value": "100073462551609",
		"domain": "facebook.com",
		"path": "/",
		"hostOnly": false,
		"creation": "2021-10-12T08:10:13.285Z",
		"lastAccessed": "2021-10-12T08:10:14.471Z"
	},
	{
		"key": "xs",
		"value": "41%3AhnVVyUe9-wS2Cg%3A2%3A1634021119%3A-1%3A-1",
		"domain": "facebook.com",
		"path": "/",
		"hostOnly": false,
		"creation": "2021-10-12T08:10:13.286Z",
		"lastAccessed": "2021-10-12T08:10:14.471Z"
	},
	{
		"key": "wd",
		"value": "598x1220",
		"domain": "facebook.com",
		"path": "/",
		"hostOnly": false,
		"creation": "2021-10-12T08:10:13.288Z",
		"lastAccessed": "2021-10-12T08:10:14.471Z"
	},
	{
		"key": "datr",
		"value": "9i5lYdOXVpjbs56s1jWtjnxB",
		"domain": "facebook.com",
		"path": "/",
		"hostOnly": false,
		"creation": "2021-10-12T08:10:13.262Z",
		"lastAccessed": "2021-10-12T08:10:14.471Z"
	},
	{
		"key": "sb",
		"value": "9i5lYYXpbvLBtWOYsGpUFCAk",
		"domain": "facebook.com",
		"path": "/",
		"hostOnly": false,
		"creation": "2021-10-12T08:10:13.268Z",
		"lastAccessed": "2021-10-12T08:10:14.471Z"
	},
	{
		"key": "m_pixel_ratio",
		"value": "1.806249976158142",
		"domain": "facebook.com",
		"path": "/",
		"hostOnly": false,
		"creation": "2021-10-12T08:10:13.272Z",
		"lastAccessed": "2021-10-12T08:10:14.471Z"
	},
	{
		"key": "fr",
		"value": "0vkc5mF7qcuOOD2zY.AWWEf1ZgGMNtPQUtgAwvrOFGLhw.BhZS72.wi.AAA.0.0.BhZS7_.AWVt_Ji-5gc",
		"domain": "facebook.com",
		"path": "/",
		"hostOnly": false,
		"creation": "2021-10-12T08:10:13.276Z",
		"lastAccessed": "2021-10-12T08:10:14.471Z"
	},
	{
		"key": "c_user",
		"value": "100073462551609",
		"domain": "facebook.com",
		"path": "/",
		"hostOnly": false,
		"creation": "2021-10-12T08:10:13.285Z",
		"lastAccessed": "2021-10-12T08:10:14.471Z"
	},
	{
		"key": "xs",
		"value": "41%3AhnVVyUe9-wS2Cg%3A2%3A1634021119%3A-1%3A-1",
		"domain": "facebook.com",
		"path": "/",
		"hostOnly": false,
		"creation": "2021-10-12T08:10:13.286Z",
		"lastAccessed": "2021-10-12T08:10:14.471Z"
	},
	{
		"key": "wd",
		"value": "598x1220",
		"domain": "facebook.com",
		"path": "/",
		"hostOnly": false,
		"creation": "2021-10-12T08:10:13.288Z",
		"lastAccessed": "2021-10-12T08:10:14.471Z"
	}
]